anti_cursing/__init__.py
anti_cursing/command.py
anti_cursing/lib.py
anti_cursing/main.py
anti_cursing/utils.py
anti_cursing/dataset/.DS_Store
anti_cursing/dataset/emoji_category.csv
anti_cursing-0.0.2.dist-info/LICENSE
anti_cursing-0.0.2.dist-info/METADATA
anti_cursing-0.0.2.dist-info/WHEEL
anti_cursing-0.0.2.dist-info/top_level.txt
anti_cursing-0.0.2.dist-info/RECORD
